g13_linux/__init__.py
g13_linux/cli.py
g13_linux/device.py
g13_linux/mapper.py
g13_linux/gui/__init__.py
g13_linux/gui/main.py
g13_linux/gui/controllers/__init__.py
g13_linux/gui/controllers/app_controller.py
g13_linux/gui/controllers/device_event_controller.py
g13_linux/gui/models/__init__.py
g13_linux/gui/models/app_profile_rules.py
g13_linux/gui/models/event_decoder.py
g13_linux/gui/models/g13_device.py
g13_linux/gui/models/global_hotkeys.py
g13_linux/gui/models/hardware_controller.py
g13_linux/gui/models/joystick_handler.py
g13_linux/gui/models/macro_manager.py
g13_linux/gui/models/macro_player.py
g13_linux/gui/models/macro_recorder.py
g13_linux/gui/models/macro_types.py
g13_linux/gui/models/profile_manager.py
g13_linux/gui/models/window_monitor.py
g13_linux/gui/resources/__init__.py
g13_linux/gui/resources/g13_layout.py
g13_linux/gui/resources/styles.py
g13_linux/gui/views/__init__.py
g13_linux/gui/views/app_profiles.py
g13_linux/gui/views/button_mapper.py
g13_linux/gui/views/hardware_control.py
g13_linux/gui/views/joystick_settings.py
g13_linux/gui/views/live_monitor.py
g13_linux/gui/views/macro_editor.py
g13_linux/gui/views/main_window.py
g13_linux/gui/views/profile_manager.py
g13_linux/gui/widgets/__init__.py
g13_linux/gui/widgets/color_picker.py
g13_linux/gui/widgets/g13_button.py
g13_linux/gui/widgets/key_selector.py
g13_linux/gui/widgets/lcd_preview.py
g13_linux/gui/widgets/macro_record_dialog.py
g13_linux/hardware/__init__.py
g13_linux/hardware/backlight.py
g13_linux/hardware/lcd.py
g13_linux-1.5.6.dist-info/licenses/LICENSE
g13_linux-1.5.6.dist-info/METADATA
g13_linux-1.5.6.dist-info/WHEEL
g13_linux-1.5.6.dist-info/entry_points.txt
g13_linux-1.5.6.dist-info/top_level.txt
g13_linux-1.5.6.dist-info/RECORD
