Metadata-Version: 2.4
Name: g13-linux
Version: 1.5.6
Summary: Logitech G13 Linux driver with macro support, RGB control, and LCD display management
Author: AreteDriver
Maintainer: AreteDriver
License-Expression: MIT
Project-URL: Homepage, https://github.com/AreteDriver/G13_Linux
Project-URL: Documentation, https://github.com/AreteDriver/G13_Linux#readme
Project-URL: Repository, https://github.com/AreteDriver/G13_Linux.git
Project-URL: Issues, https://github.com/AreteDriver/G13_Linux/issues
Project-URL: Changelog, https://github.com/AreteDriver/G13_Linux/blob/main/CHANGELOG.md
Keywords: logitech,g13,linux,driver,gaming,keyboard,macro,rgb,lcd,hid,usb
Classifier: Development Status :: 4 - Beta
Classifier: Environment :: Console
Classifier: Environment :: X11 Applications :: Qt
Classifier: Intended Audience :: End Users/Desktop
Classifier: Intended Audience :: Developers
Classifier: Operating System :: POSIX :: Linux
Classifier: Programming Language :: Python :: 3
Classifier: Programming Language :: Python :: 3.10
Classifier: Programming Language :: Python :: 3.11
Classifier: Programming Language :: Python :: 3.12
Classifier: Topic :: System :: Hardware :: Hardware Drivers
Classifier: Topic :: Games/Entertainment
Classifier: Topic :: Desktop Environment
Requires-Python: >=3.10
License-File: LICENSE
Requires-Dist: hidapi>=0.10.0
Requires-Dist: evdev>=1.4.0
Requires-Dist: pyusb>=1.2.0
Requires-Dist: PyQt6>=6.4.0
Requires-Dist: pynput>=1.7.0
Requires-Dist: Pillow>=9.0.0
Provides-Extra: dev
Requires-Dist: pytest>=7.0.0; extra == "dev"
Requires-Dist: pytest-cov>=4.0.0; extra == "dev"
Requires-Dist: pytest-qt>=4.2.0; extra == "dev"
Requires-Dist: ruff>=0.1.0; extra == "dev"
Requires-Dist: mypy>=1.0.0; extra == "dev"
Requires-Dist: build>=0.10.0; extra == "dev"
Requires-Dist: twine>=4.0.0; extra == "dev"
Dynamic: license-file
